{
  "products": [
    {
      "id": 1,
      "name": "Classic Smash Burger Box",
      "description": "البرجر الكلاسيكي الأصيل — لحمة سميكة مع جبن أمريكي",
      "price": 189,
      "badge": null,
      "image": "/ref/IMG-20260615-WA0026.jpg",
      "category": "boxes",
      "ingredients": [
        "لحمة بقر 180g",
        "جبن أمريكي",
        "خس",
        "طماطم",
        "بصل مكرمل",
        "صوص Burger Box الخاص"
      ],
      "prepSteps": [
        "سخن المقلاة على نار عالية",
        "حط اللحمة واسحقها بالمقلاة 3 دقايق",
        "اقلبها وحط الجبن فوقها",
        "ركّب السندوتش وبالهنا"
      ]
    },
    {
      "id": 2,
      "name": "Spicy Crispy Box",
      "description": "برجر حار وقرمشي — مش لضعاف القلب",
      "price": 219,
      "badge": "🌶️ حار",
      "image": "/ref/IMG-20260615-WA0026.jpg",
      "category": "boxes",
      "ingredients": [
        "لحمة دجاج مقلية",
        "صوص فلفل حار",
        "كول سلو",
        "مخلل جالبينيو",
        "خبز بريوش"
      ],
      "prepSteps": [
        "سخن الزيت على 180 درجة",
        "قلي الدجاج 6-8 دقايق",
        "صفّيه وركّب السندوتش"
      ]
    },
    {
      "id": 3,
      "name": "Premium Wagyu Box",
      "description": "تجربة راقية مع لحمة واغيو الفاخرة",
      "price": 349,
      "badge": "⭐ Premium",
      "image": "/ref/IMG-20260615-WA0026.jpg",
      "category": "boxes",
      "ingredients": [
        "لحمة واغيو 200g",
        "جبن تريفل",
        "أفوكادو",
        "أروجولا",
        "صوص ترياكي",
        "خبز بريوش أسود"
      ],
      "prepSteps": [
        "سخن الجريل على نار متوسطة-عالية",
        "اشوي اللحمة 4 دقايق كل جهة",
        "استنّيها ترتاح دقيقتين قبل التقديم"
      ]
    },
    {
      "id": 4,
      "name": "Double Smash Box",
      "description": "ضعف اللحم، ضعف المتعة",
      "price": 259,
      "badge": "🔥 الأكثر مبيعاً",
      "image": "/ref/IMG-20260615-WA0026.jpg",
      "category": "boxes",
      "ingredients": [
        "لحمتين بقر 150g",
        "جبن شيدر مزدوج",
        "بيض مقلي",
        "بيكون",
        "صوص Burger Box Supreme"
      ],
      "prepSteps": [
        "اعمل الخطوات نفس Classic Smash",
        "أضف البيض المقلي فوق الجبن",
        "ركّب الطبقتين"
      ]
    },
    {
      "id": 5,
      "name": "BBQ Smoky Box",
      "description": "برجر بنكهة الشواء والدخان الأصيل",
      "price": 229,
      "badge": null,
      "image": "/ref/IMG-20260615-WA0026.jpg",
      "category": "boxes",
      "ingredients": [
        "لحمة بقر 200g",
        "صوص BBQ مدخن",
        "بصل مكرمل",
        "جبن سموك",
        "خيار مخلل"
      ],
      "prepSteps": [
        "شوّي اللحمة على نار متوسطة 5 دقايق كل جهة",
        "دهن صوص BBQ آخر دقيقة",
        "ركّب مع البصل المكرمل"
      ]
    },
    {
      "id": 6,
      "name": "Veggie Power Box",
      "description": "بوكس نباتي مش هتحس إنك بتفوّت حاجة",
      "price": 169,
      "badge": "🌱 نباتي",
      "image": "/ref/IMG-20260615-WA0026.jpg",
      "category": "boxes",
      "ingredients": [
        "باتي فطر بورتوبيلو",
        "جبن موزاريلا",
        "فلفل مشوي",
        "بيستو",
        "خبز سياباتا"
      ],
      "prepSteps": [
        "شوّي الفطر على نار عالية دقيقتين كل جهة",
        "حط الجبن وغطّيه لحظة",
        "ركّب مع الفلفل والبيستو"
      ]
    },
    {
      "id": 7,
      "name": "BURGO Family Box (4 Pieces - 600g)",
      "description": "بوكس برجر بورجو العائلي المميز (4 قطع برجر 600 جم محشية جبن شيدر أمريكي غني فاخر وممتاز، 4 عيش بافلو، صوصات ومخلل).",
      "price": 250,
      "badge": "⭐ عائلي",
      "image": "/ref/IMG-20260615-WA0027.jpg",
      "category": "boxes",
      "ingredients": [
        "4 قطع برجر أنجوس 150جم محشية شيدر",
        "4 قطع خبز بافلو المميز",
        "خيار مخلل مقرمش 100 جم",
        "صوص باربكيو 25 جم وصوص رانش 25 جم",
        "شيدر أمريكي وكاتشب"
      ],
      "prepSteps": [
        "اشوي قطع البرجر على جريل ساخن 4-5 دقائق لكل جهة",
        "قم بتحميص خبز بافلو قليلاً",
        "أضف الخيار المخلل والصوصات المفضلة لديك",
        "ركّب السندوتشات واستمتع مع العائلة"
      ]
    },
    {
      "id": 8,
      "name": "BURGO Mega Box (7 Pieces - 1050g)",
      "description": "بوكس برجر بورجو الضخم المثالي للمجموعات (7 قطع برجر 1050 جم محشية جبن شيدر أمريكي غني فاخر وممتاز، 7 عيش بافلو، صوصات ومخلل).",
      "price": 450,
      "badge": "🔥 التوفير الأكبر",
      "image": "/ref/IMG-20260615-WA0027.jpg",
      "category": "boxes",
      "ingredients": [
        "7 قطع برجر أنجوس 150جم محشية شيدر",
        "7 قطع خبز بافلو المميز",
        "خيار مخلل مقرمش 100 جم",
        "صوصات باربكيو ورانش متنوعة",
        "شرائح جبن شيدر إضافية وكاتشب"
      ],
      "prepSteps": [
        "اشوي قطع البرجر على جريل ساخن 4-5 دقائق لكل جهة",
        "حمص خبز بافلو اللذيذ",
        "وزع الصوصات والمخلل بالتساوي",
        "استمتع باللمة وطعم بورجو الأصيل"
      ]
    },
    {
      "id": 9,
      "name": "French Fries (200g)",
      "description": "بطاطس مقلية مقرمشة وذهبية محضرة بأعلى جودة.",
      "price": 40,
      "badge": "🍟 كلاسيك",
      "image": "/ref/IMG-20260615-WA0034.jpg",
      "category": "appetizers",
      "ingredients": [
        "بطاطس أصابع طازجة",
        "ملح بحري خفيف"
      ],
      "prepSteps": [
        "سخن الزيت أو القلاية الهوائية",
        "اقلِ البطاطس حتى تصبح ذهبية ومقرمشة",
        "أضف الملح والتوابل المفضلة لديك وقدمها ساخنة"
      ]
    },
    {
      "id": 10,
      "name": "Crinkle-cut Fries (200g)",
      "description": "بطاطس مقلية مموجة (كرانكل كت) مقرمشة بشكل رائع ونكهة غنية.",
      "price": 55,
      "badge": "✨ مميز",
      "image": "/ref/IMG-20260615-WA0035.jpg",
      "category": "appetizers",
      "ingredients": [
        "بطاطس كرانكل كت مموجة",
        "ملح وتوابل بورجو الخاصة"
      ],
      "prepSteps": [
        "اقلها في زيت غزير ساخن لمدة 4-5 دقائق",
        "صفها جيداً من الزيت",
        "قدمها مع صوص الشيدر أو الكاتشب"
      ]
    },
    {
      "id": 11,
      "name": "Onion Rings (200g)",
      "description": "من أجود أنواع حلقات البصل الأمريكية المقرمشة، محضرة بعناية لتكون الرفيق المثالي لوجبتك.",
      "price": 70,
      "badge": "🧅 مقرمش جداً",
      "image": "/ref/IMG-20260615-WA0033.jpg",
      "category": "appetizers",
      "ingredients": [
        "حلقات بصل طازجة مغطاة بفتات الخبز الذهبي"
      ],
      "prepSteps": [
        "اقلها في زيت ساخن حتى تأخذ لوناً ذهبياً غامقاً",
        "قدمها مباشرة وهي ساخنة للحفاظ على القرمشة"
      ]
    },
    {
      "id": 12,
      "name": "Angus Burger Patty (150g)",
      "description": "قطعة برجر أمريكي من لحم الأنجوس الفاخر، محشية بجبنة شيدر أمريكي غنية وفاخرة لتجربة لا تُنسى.",
      "price": 80,
      "badge": "🥩 لحم أنجوس فاخر",
      "image": "/ref/IMG-20260615-WA0036.jpg",
      "category": "addons",
      "ingredients": [
        "لحم أنجوس فاخر 150 جم",
        "حشوة جبن شيدر أمريكي أصلي"
      ],
      "prepSteps": [
        "اشوِ القطعة على جريل ساخن",
        "لا تقم بالضغط عليها أثناء الشوي للحفاظ على حشوة الشيدر بالداخل"
      ]
    },
    {
      "id": 13,
      "name": "Buffalo Bread (عيش بافلو المميز)",
      "description": "خبز البافلو المميز، هش، طري، وطازج، يُخبز يومياً ليضيف لمسة مثالية لكل ساندوتش.",
      "price": 15,
      "badge": "🍞 طازج يومياً",
      "image": "/ref/IMG-20260615-WA0038.jpg",
      "category": "addons",
      "ingredients": [
        "دقيق فاخر، خميرة، حليب، زبدة"
      ],
      "prepSteps": [
        "افتح الخبز من المنتصف ونصف حمصه على الجريل مع القليل من الزبدة"
      ]
    },
    {
      "id": 14,
      "name": "Pickled Cucumber (100g)",
      "description": "خيار مخلل أمريكي مقرمش ومختار بعناية، يضيف النكهة الحامضة والمنعشة التي تجعل تجربة البرجر مكتملة.",
      "price": 30,
      "badge": "🥒 مقرمش وحامض",
      "image": "/ref/IMG-20260615-WA0039.jpg",
      "category": "addons",
      "ingredients": [
        "خيار مخلل شرائح أمريكي مقرمش"
      ],
      "prepSteps": [
        "أضف شرائح الخيار المخلل فوق شريحة البرجر والجبن مباشرة"
      ]
    },
    {
      "id": 15,
      "name": "BBQ Sauce (25g)",
      "description": "صوص باربكيو مدخن غني ولذيذ مثالي للتغميس وإضافة نكهة الشواء.",
      "price": 7.5,
      "badge": "🔥 مدخن",
      "image": "/ref/IMG-20260615-WA0027.jpg",
      "category": "addons",
      "ingredients": [
        "صوص باربكيو مدخن فاخر"
      ],
      "prepSteps": [
        "يقدم كغموس جانبي أو يدهن على الخبز"
      ]
    },
    {
      "id": 16,
      "name": "Ranch Sauce (25g)",
      "description": "صوص رانش كريمي غني بنكهة الثوم والأعشاب اللذيذة.",
      "price": 12,
      "badge": "🌿 كريمي",
      "image": "/ref/IMG-20260615-WA0027.jpg",
      "category": "addons",
      "ingredients": [
        "صوص رانش كريمي بالأعشاب"
      ],
      "prepSteps": [
        "يقدم كغموس جانبي للبطاطس وحلقات البصل"
      ]
    },
    {
      "id": 17,
      "name": "Cheddar Cheese Sauce (15g)",
      "description": "صوص شيدر مميز، غني، وساخن، يضفي نكهة لا تُقاوم تجعل وجبتك أكثر متعة وجاذبية.",
      "price": 12,
      "badge": "🧀 جبن غني",
      "image": "/ref/IMG-20260615-WA0037.jpg",
      "category": "addons",
      "ingredients": [
        "صوص جبنة شيدر غني 15 جرام"
      ],
      "prepSteps": [
        "سخن الكيس قليلاً بالماء الدافئ ثم اسكبه فوق البرجر أو البطاطس"
      ]
    },
    {
      "id": 18,
      "name": "Ketchup Sauce (140g)",
      "description": "باكت كاتشب من أجود الأنواع المتاحة، مذاق غني يساعد على التغميس ويبرز نكهة البرجر والبطاطس المميزة.",
      "price": 20,
      "badge": "🍅 غني بالطماطم",
      "image": "/ref/IMG-20260615-WA0040.jpg",
      "category": "addons",
      "ingredients": [
        "كاتشب طماطم طبيعي 140 جرام"
      ],
      "prepSteps": [
        "افتح الباكت واستخدمه للتغميس أو صبه داخل الساندوتش"
      ]
    }
  ],
  "orders": [
    {
      "id": "65199",
      "customerName": "ggg",
      "phone": "01207091650",
      "address": "5 شارع مدرسة ابو يوسف",
      "governorate": "الإسكندرية",
      "notes": "",
      "items": [
        {
          "id": 5,
          "name": "BBQ Smoky Box",
          "price": 229,
          "quantity": 1,
          "image": "/ref/IMG-20260615-WA0026.jpg"
        },
        {
          "id": 6,
          "name": "Veggie Power Box",
          "price": 169,
          "quantity": 1,
          "image": "/ref/IMG-20260615-WA0026.jpg"
        }
      ],
      "total": 398,
      "paymentMethod": "card",
      "status": "delivered",
      "createdAt": "2026-06-15T02:27:35.216Z"
    }
  ]
}